ribs/__init__.py
ribs/_utils.py
ribs/py.typed
ribs/typing.py
ribs/archives/__init__.py
ribs/archives/_add_status.py
ribs/archives/_archive_base.py
ribs/archives/_archive_data_frame.py
ribs/archives/_archive_stats.py
ribs/archives/_array_store.py
ribs/archives/_categorical_archive.py
ribs/archives/_cqd_score.py
ribs/archives/_cvt_archive.py
ribs/archives/_density_archive.py
ribs/archives/_grid_archive.py
ribs/archives/_proximity_archive.py
ribs/archives/_sliding_boundaries_archive.py
ribs/archives/_utils.py
ribs/emitters/__init__.py
ribs/emitters/_bayesian_opt_emitter.py
ribs/emitters/_emitter_base.py
ribs/emitters/_evolution_strategy_emitter.py
ribs/emitters/_gaussian_emitter.py
ribs/emitters/_genetic_algorithm_emitter.py
ribs/emitters/_gradient_arborescence_emitter.py
ribs/emitters/_gradient_operator_emitter.py
ribs/emitters/_iso_line_emitter.py
ribs/emitters/rankers.py
ribs/emitters/operators/__init__.py
ribs/emitters/operators/_gaussian.py
ribs/emitters/operators/_iso_line.py
ribs/emitters/operators/_operator_base.py
ribs/emitters/opt/__init__.py
ribs/emitters/opt/_adam_opt.py
ribs/emitters/opt/_cma_es.py
ribs/emitters/opt/_evolution_strategy_base.py
ribs/emitters/opt/_gradient_ascent_opt.py
ribs/emitters/opt/_gradient_opt_base.py
ribs/emitters/opt/_lm_ma_es.py
ribs/emitters/opt/_openai_es.py
ribs/emitters/opt/_pycma_es.py
ribs/emitters/opt/_sep_cma_es.py
ribs/schedulers/__init__.py
ribs/schedulers/_bandit_scheduler.py
ribs/schedulers/_bayesian_opt_scheduler.py
ribs/schedulers/_scheduler.py
ribs/visualize/__init__.py
ribs/visualize/_cvt_archive_3d_plot.py
ribs/visualize/_cvt_archive_heatmap.py
ribs/visualize/_grid_archive_heatmap.py
ribs/visualize/_parallel_axes_plot.py
ribs/visualize/_proximity_archive_plot.py
ribs/visualize/_sliding_boundaries_archive_heatmap.py
ribs/visualize/_utils.py
ribs/visualize/_visualize_qdax.py
ribs-0.9.0.dist-info/licenses/LICENSE
ribs-0.9.0.dist-info/METADATA
ribs-0.9.0.dist-info/WHEEL
ribs-0.9.0.dist-info/top_level.txt
ribs-0.9.0.dist-info/RECORD
