Metadata-Version: 2.4
Name: ribs
Version: 0.9.0
Summary: A bare-bones Python library for quality diversity optimization.
Author-email: ICAROS Lab pyribs Team <team@pyribs.org>
License-Expression: MIT
Project-URL: Homepage, https://pyribs.org
Project-URL: Repository, https://github.com/icaros-usc/pyribs
Project-URL: Documentation, https://docs.pyribs.org
Keywords: ribs,quality diversity,optimization
Classifier: Development Status :: 4 - Beta
Classifier: Intended Audience :: Developers
Classifier: Intended Audience :: Education
Classifier: Intended Audience :: Science/Research
Classifier: Natural Language :: English
Classifier: Programming Language :: Python :: 3
Classifier: Programming Language :: Python :: 3.10
Classifier: Programming Language :: Python :: 3.11
Classifier: Programming Language :: Python :: 3.12
Classifier: Programming Language :: Python :: 3.13
Classifier: Programming Language :: Python :: 3.14
Classifier: Topic :: Scientific/Engineering
Classifier: Topic :: Scientific/Engineering :: Mathematics
Classifier: Topic :: Scientific/Engineering :: Artificial Intelligence
Requires-Python: >=3.10.0
License-File: LICENSE
Requires-Dist: array_api_compat
Requires-Dist: numba>=0.51.0
Requires-Dist: numpy>=2.0.0
Requires-Dist: numpy_groupies>=0.9.16
Requires-Dist: pandas>=1.0.0
Requires-Dist: scikit-learn>=1.1.0
Requires-Dist: scipy>=1.7.0
Requires-Dist: sortedcontainers>=2.0.0
Requires-Dist: threadpoolctl>=3.0.0
Requires-Dist: typing-extensions>=4.12.0
Provides-Extra: visualize
Requires-Dist: matplotlib>=3.0.0; extra == "visualize"
Requires-Dist: shapely>=2.0.0; extra == "visualize"
Provides-Extra: all
Requires-Dist: matplotlib>=3.0.0; extra == "all"
Requires-Dist: shapely>=2.0.0; extra == "all"
Requires-Dist: cma; extra == "all"
Requires-Dist: pymoo; extra == "all"
Provides-Extra: dev
Requires-Dist: ruff>=0.13.0; extra == "dev"
Requires-Dist: ty; extra == "dev"
Requires-Dist: pre-commit; extra == "dev"
Requires-Dist: python-box[all]~=7.0; extra == "dev"
Requires-Dist: pytest==8.3.5; extra == "dev"
Requires-Dist: pytest-cov==6.0.0; extra == "dev"
Requires-Dist: pytest-benchmark==5.1.0; extra == "dev"
Requires-Dist: pytest-xdist==3.8.0; extra == "dev"
Requires-Dist: myst-nb==1.3.0; extra == "dev"
Requires-Dist: Sphinx==8.1.3; extra == "dev"
Requires-Dist: sphinx-autobuild==2021.3.14; extra == "dev"
Requires-Dist: sphinx-autodoc-typehints==3.0.1; extra == "dev"
Requires-Dist: sphinx-jinja2-compat==0.4.1; extra == "dev"
Requires-Dist: sphinx-prompt==1.9.0; extra == "dev"
Requires-Dist: sphinx-tabs==3.4.5; extra == "dev"
Requires-Dist: sphinx-toolbox==4.0.0; extra == "dev"
Requires-Dist: sphinx_immaterial==0.13.5; extra == "dev"
Requires-Dist: sphinxcontrib-applehelp==2.0.0; extra == "dev"
Requires-Dist: sphinxcontrib-devhelp==2.0.0; extra == "dev"
Requires-Dist: sphinxcontrib-htmlhelp==2.1.0; extra == "dev"
Requires-Dist: sphinxcontrib-jsmath==1.0.1; extra == "dev"
Requires-Dist: sphinxcontrib-qthelp==2.0.0; extra == "dev"
Requires-Dist: sphinxcontrib-serializinghtml==2.0.0; extra == "dev"
Requires-Dist: sphinxcontrib-svg2pdfconverter==1.3.0; extra == "dev"
Requires-Dist: minify-html==0.15.0; extra == "dev"
Requires-Dist: beautifulsoup4==4.13.4; extra == "dev"
Requires-Dist: build; extra == "dev"
Requires-Dist: check-wheel-contents; extra == "dev"
Requires-Dist: twine; extra == "dev"
Provides-Extra: dev-array-api
Requires-Dist: torch; extra == "dev-array-api"
Requires-Dist: cupy-cuda12x; extra == "dev-array-api"
Dynamic: license-file
